aws_close_account/__init__.py
aws_close_account/__main__.py
aws_close_account-0.3.2.dist-info/LICENSE
aws_close_account-0.3.2.dist-info/METADATA
aws_close_account-0.3.2.dist-info/WHEEL
aws_close_account-0.3.2.dist-info/entry_points.txt
aws_close_account-0.3.2.dist-info/top_level.txt
aws_close_account-0.3.2.dist-info/RECORD
