Metadata-Version: 2.1
Name: aws-close-account
Version: 0.3.2
Summary: Programmatically close an AWS account using Selenium 
Home-page: https://github.com/JohannesEbke/aws_close_account
Author: Johannes Ebke
Author-email: johannes@ebke.org
Keywords: aws account selenium
Classifier: Development Status :: 4 - Beta
Classifier: Environment :: Console
Classifier: Intended Audience :: Developers
Classifier: License :: OSI Approved :: MIT License
Classifier: Natural Language :: English
Classifier: Programming Language :: Python :: 3
Classifier: Programming Language :: Python :: 3.9
Classifier: Programming Language :: Python :: 3.10
License-File: LICENSE
Requires-Dist: selenium (>=4.1.0)
